{
  "Subject": "The gaming industry",
  "Words": [
    "MULTIPLAYER",
    "FRANCHISE",
    "EMULATOR",
    "STREAMER",
    "JOYSTICK",
    "ESPORTS",
    "CONSOLE"
  ],
  "Matrix": [
    [
      "R",
      "Y",
      "S",
      "N",
      "Q",
      "E",
      "A",
      "R",
      "P",
      "J",
      "E"
    ],
    [
      "X",
      "E",
      "Y",
      "T",
      "Q",
      "C",
      "E",
      "R",
      "T",
      "O",
      "M"
    ],
    [
      "B",
      "T",
      "Y",
      "M",
      "R",
      "M",
      "Y",
      "E",
      "P",
      "Y",
      "U"
    ],
    [
      "Q",
      "O",
      "Z",
      "A",
      "A",
      "O",
      "E",
      "W",
      "P",
      "S",
      "L"
    ],
    [
      "D",
      "X",
      "W",
      "E",
      "L",
      "L",
      "P",
      "R",
      "F",
      "T",
      "A"
    ],
    [
      "L",
      "B",
      "R",
      "I",
      "O",
      "P",
      "J",
      "S",
      "P",
      "I",
      "T"
    ],
    [
      "S",
      "T",
      "H",
      "S",
      "Y",
      "W",
      "I",
      "A",
      "E",
      "C",
      "O"
    ],
    [
      "S",
      "Q",
      "N",
      "E",
      "Q",
      "T",
      "P",
      "T",
      "T",
      "K",
      "R"
    ],
    [
      "S",
      "O",
      "D",
      "H",
      "C",
      "D",
      "B",
      "T",
      "L",
      "N",
      "Y"
    ],
    [
      "C",
      "H",
      "Y",
      "C",
      "V",
      "X",
      "D",
      "C",
      "R",
      "U",
      "K"
    ],
    [
      "B",
      "M",
      "D",
      "G",
      "I",
      "R",
      "R",
      "L",
      "I",
      "L",
      "M"
    ],
    [
      "Z",
      "E",
      "S",
      "I",
      "H",
      "C",
      "N",
      "A",
      "R",
      "F",
      "I"
    ]
  ],
  "Width": 11,
  "Height": 12,
  "FakeLetters": [
    {
      "X": 1,
      "Y": 0
    },
    {
      "X": 3,
      "Y": 0
    },
    {
      "X": 4,
      "Y": 0
    },
    {
      "X": 5,
      "Y": 0
    },
    {
      "X": 6,
      "Y": 0
    },
    {
      "X": 8,
      "Y": 0
    },
    {
      "X": 0,
      "Y": 1
    },
    {
      "X": 2,
      "Y": 1
    },
    {
      "X": 4,
      "Y": 1
    },
    {
      "X": 5,
      "Y": 1
    },
    {
      "X": 7,
      "Y": 1
    },
    {
      "X": 8,
      "Y": 1
    },
    {
      "X": 0,
      "Y": 2
    },
    {
      "X": 1,
      "Y": 2
    },
    {
      "X": 3,
      "Y": 2
    },
    {
      "X": 6,
      "Y": 2
    },
    {
      "X": 7,
      "Y": 2
    },
    {
      "X": 8,
      "Y": 2
    },
    {
      "X": 0,
      "Y": 3
    },
    {
      "X": 1,
      "Y": 3
    },
    {
      "X": 2,
      "Y": 3
    },
    {
      "X": 7,
      "Y": 3
    },
    {
      "X": 8,
      "Y": 3
    },
    {
      "X": 0,
      "Y": 4
    },
    {
      "X": 1,
      "Y": 4
    },
    {
      "X": 2,
      "Y": 4
    },
    {
      "X": 7,
      "Y": 4
    },
    {
      "X": 8,
      "Y": 4
    },
    {
      "X": 0,
      "Y": 5
    },
    {
      "X": 1,
      "Y": 5
    },
    {
      "X": 3,
      "Y": 5
    },
    {
      "X": 6,
      "Y": 5
    },
    {
      "X": 8,
      "Y": 5
    },
    {
      "X": 0,
      "Y": 6
    },
    {
      "X": 2,
      "Y": 6
    },
    {
      "X": 4,
      "Y": 6
    },
    {
      "X": 5,
      "Y": 6
    },
    {
      "X": 7,
      "Y": 6
    },
    {
      "X": 1,
      "Y": 7
    },
    {
      "X": 3,
      "Y": 7
    },
    {
      "X": 4,
      "Y": 7
    },
    {
      "X": 5,
      "Y": 7
    },
    {
      "X": 6,
      "Y": 7
    },
    {
      "X": 8,
      "Y": 7
    },
    {
      "X": 0,
      "Y": 8
    },
    {
      "X": 2,
      "Y": 8
    },
    {
      "X": 3,
      "Y": 8
    },
    {
      "X": 4,
      "Y": 8
    },
    {
      "X": 5,
      "Y": 8
    },
    {
      "X": 6,
      "Y": 8
    },
    {
      "X": 7,
      "Y": 8
    },
    {
      "X": 9,
      "Y": 8
    },
    {
      "X": 10,
      "Y": 8
    },
    {
      "X": 1,
      "Y": 9
    },
    {
      "X": 2,
      "Y": 9
    },
    {
      "X": 3,
      "Y": 9
    },
    {
      "X": 4,
      "Y": 9
    },
    {
      "X": 5,
      "Y": 9
    },
    {
      "X": 6,
      "Y": 9
    },
    {
      "X": 7,
      "Y": 9
    },
    {
      "X": 8,
      "Y": 9
    },
    {
      "X": 10,
      "Y": 9
    },
    {
      "X": 0,
      "Y": 10
    },
    {
      "X": 1,
      "Y": 10
    },
    {
      "X": 2,
      "Y": 10
    },
    {
      "X": 3,
      "Y": 10
    },
    {
      "X": 4,
      "Y": 10
    },
    {
      "X": 5,
      "Y": 10
    },
    {
      "X": 6,
      "Y": 10
    },
    {
      "X": 7,
      "Y": 10
    },
    {
      "X": 8,
      "Y": 10
    },
    {
      "X": 9,
      "Y": 10
    },
    {
      "X": 0,
      "Y": 11
    },
    {
      "X": 10,
      "Y": 11
    }
  ],
  "FirstLetters": [
    {
      "X": 10,
      "Y": 10
    },
    {
      "X": 9,
      "Y": 11
    },
    {
      "X": 10,
      "Y": 0
    },
    {
      "X": 0,
      "Y": 7
    },
    {
      "X": 9,
      "Y": 0
    },
    {
      "X": 8,
      "Y": 6
    },
    {
      "X": 0,
      "Y": 9
    }
  ],
  "LastLetters": [
    {
      "X": 0,
      "Y": 0
    },
    {
      "X": 1,
      "Y": 11
    },
    {
      "X": 10,
      "Y": 7
    },
    {
      "X": 7,
      "Y": 0
    },
    {
      "X": 9,
      "Y": 7
    },
    {
      "X": 2,
      "Y": 0
    },
    {
      "X": 6,
      "Y": 3
    }
  ]
}