{
  "Subject": "Graffiti",
  "Words": [
    "LETTERING",
    "WILDSTYLE",
    "FREESTYLE",
    "BURNER",
    "BUBBLE",
    "PIECE",
    "CREW"
  ],
  "Matrix": [
    [
      "E",
      "I",
      "K",
      "V",
      "N",
      "V",
      "R",
      "L",
      "E"
    ],
    [
      "L",
      "C",
      "T",
      "P",
      "E",
      "E",
      "B",
      "E",
      "C"
    ],
    [
      "Y",
      "E",
      "W",
      "W",
      "R",
      "I",
      "R",
      "T",
      "E"
    ],
    [
      "T",
      "L",
      "W",
      "C",
      "U",
      "E",
      "B",
      "T",
      "I"
    ],
    [
      "S",
      "M",
      "X",
      "E",
      "N",
      "R",
      "U",
      "E",
      "P"
    ],
    [
      "D",
      "U",
      "W",
      "R",
      "R",
      "V",
      "B",
      "R",
      "M"
    ],
    [
      "L",
      "L",
      "U",
      "X",
      "T",
      "C",
      "B",
      "I",
      "R"
    ],
    [
      "I",
      "B",
      "P",
      "H",
      "Q",
      "S",
      "L",
      "N",
      "C"
    ],
    [
      "W",
      "X",
      "S",
      "B",
      "T",
      "G",
      "E",
      "G",
      "U"
    ],
    [
      "F",
      "R",
      "E",
      "E",
      "S",
      "T",
      "Y",
      "L",
      "E"
    ]
  ],
  "Width": 9,
  "Height": 10,
  "FakeLetters": [
    {
      "X": 1,
      "Y": 0
    },
    {
      "X": 2,
      "Y": 0
    },
    {
      "X": 3,
      "Y": 0
    },
    {
      "X": 4,
      "Y": 0
    },
    {
      "X": 5,
      "Y": 0
    },
    {
      "X": 6,
      "Y": 0
    },
    {
      "X": 1,
      "Y": 1
    },
    {
      "X": 2,
      "Y": 1
    },
    {
      "X": 3,
      "Y": 1
    },
    {
      "X": 4,
      "Y": 1
    },
    {
      "X": 5,
      "Y": 1
    },
    {
      "X": 6,
      "Y": 1
    },
    {
      "X": 1,
      "Y": 2
    },
    {
      "X": 2,
      "Y": 2
    },
    {
      "X": 3,
      "Y": 2
    },
    {
      "X": 4,
      "Y": 2
    },
    {
      "X": 5,
      "Y": 2
    },
    {
      "X": 1,
      "Y": 3
    },
    {
      "X": 3,
      "Y": 3
    },
    {
      "X": 4,
      "Y": 3
    },
    {
      "X": 1,
      "Y": 4
    },
    {
      "X": 2,
      "Y": 4
    },
    {
      "X": 5,
      "Y": 4
    },
    {
      "X": 1,
      "Y": 5
    },
    {
      "X": 2,
      "Y": 5
    },
    {
      "X": 5,
      "Y": 5
    },
    {
      "X": 8,
      "Y": 5
    },
    {
      "X": 1,
      "Y": 6
    },
    {
      "X": 3,
      "Y": 6
    },
    {
      "X": 4,
      "Y": 6
    },
    {
      "X": 8,
      "Y": 6
    },
    {
      "X": 2,
      "Y": 7
    },
    {
      "X": 3,
      "Y": 7
    },
    {
      "X": 4,
      "Y": 7
    },
    {
      "X": 5,
      "Y": 7
    },
    {
      "X": 8,
      "Y": 7
    },
    {
      "X": 1,
      "Y": 8
    },
    {
      "X": 2,
      "Y": 8
    },
    {
      "X": 3,
      "Y": 8
    },
    {
      "X": 4,
      "Y": 8
    },
    {
      "X": 5,
      "Y": 8
    },
    {
      "X": 8,
      "Y": 8
    }
  ],
  "FirstLetters": [
    {
      "X": 7,
      "Y": 0
    },
    {
      "X": 0,
      "Y": 8
    },
    {
      "X": 0,
      "Y": 9
    },
    {
      "X": 1,
      "Y": 7
    },
    {
      "X": 6,
      "Y": 3
    },
    {
      "X": 8,
      "Y": 4
    },
    {
      "X": 5,
      "Y": 6
    }
  ],
  "LastLetters": [
    {
      "X": 7,
      "Y": 8
    },
    {
      "X": 0,
      "Y": 0
    },
    {
      "X": 8,
      "Y": 9
    },
    {
      "X": 6,
      "Y": 2
    },
    {
      "X": 6,
      "Y": 8
    },
    {
      "X": 8,
      "Y": 0
    },
    {
      "X": 2,
      "Y": 3
    }
  ]
}